pycapacity/__init__.py
pycapacity/algorithms.py
pycapacity/examples.py
pycapacity/human.py
pycapacity/objects.py
pycapacity/robot.py
pycapacity/visual.py
pycapacity-2.1.7.dist-info/LICENSE
pycapacity-2.1.7.dist-info/METADATA
pycapacity-2.1.7.dist-info/WHEEL
pycapacity-2.1.7.dist-info/top_level.txt
pycapacity-2.1.7.dist-info/RECORD
