Metadata-Version: 2.2
Name: pycapacity
Version: 2.1.7
Summary: A real-time task space capacity calculation module for robotic manipulators and human musculoskeletal models
Home-page: https://github.com/auctus-team/pycapacity
Author: Antun Skuric
Author-email: antun.skuric@inria.fr
License: MIT
Classifier: Programming Language :: Python :: 3
Classifier: License :: OSI Approved :: MIT License
Classifier: Operating System :: OS Independent
Classifier: Framework :: Robot Framework
Classifier: Framework :: Robot Framework :: Library
Classifier: Framework :: Robot Framework :: Tool
License-File: LICENSE
Requires-Dist: numpy
Requires-Dist: scipy
Requires-Dist: cvxopt>=1.2.6
Requires-Dist: matplotlib
Dynamic: author
Dynamic: author-email
Dynamic: classifier
Dynamic: description
Dynamic: description-content-type
Dynamic: home-page
Dynamic: license
Dynamic: requires-dist
Dynamic: summary
